expt_logger/__init__.py
expt_logger/buffer.py
expt_logger/client.py
expt_logger/config.py
expt_logger/env.py
expt_logger/exceptions.py
expt_logger/py.typed
expt_logger/run.py
expt_logger/types.py
expt_logger/validation.py
expt_logger-0.1.0.dev16.dist-info/METADATA
expt_logger-0.1.0.dev16.dist-info/WHEEL
expt_logger-0.1.0.dev16.dist-info/RECORD
