Metadata-Version: 2.4
Name: expt-logger
Version: 0.1.0.dev16
Summary: Simple experiment logging library
Requires-Python: >=3.10
Requires-Dist: requests>=2.31.0
